django_secure_password_input/__init__.py
django_secure_password_input/apps.py
django_secure_password_input/fields.py
django_secure_password_input/settings.py
django_secure_password_input/urls.py
django_secure_password_input/views.py
django_secure_password_input/widgets.py
django_secure_password_input/migrations/__init__.py
django_secure_password_input/static/django-secure-password-input/js/enable-jsencrypt.js
django_secure_password_input/static/django-secure-password-input/js/jsencrypt.js
django_secure_password_input/static/django-secure-password-input/js/jsencrypt.min.js
django_secure_password_input-0.1.6.dist-info/licenses/LICENSE
django_secure_password_input-0.1.6.dist-info/METADATA
django_secure_password_input-0.1.6.dist-info/WHEEL
django_secure_password_input-0.1.6.dist-info/top_level.txt
django_secure_password_input-0.1.6.dist-info/RECORD
